CHANGES.txt
COPYRIGHT.txt
LICENSE.txt
README.txt
bootstrap.py
buildout.cfg
setup.py
src/zamplugin/__init__.py
src/zamplugin.error.egg-info/PKG-INFO
src/zamplugin.error.egg-info/SOURCES.txt
src/zamplugin.error.egg-info/dependency_links.txt
src/zamplugin.error.egg-info/namespace_packages.txt
src/zamplugin.error.egg-info/not-zip-safe
src/zamplugin.error.egg-info/requires.txt
src/zamplugin.error.egg-info/top_level.txt
src/zamplugin/error/README.txt
src/zamplugin/error/__init__.py
src/zamplugin/error/app.zcml
src/zamplugin/error/browser.py
src/zamplugin/error/browser.zcml
src/zamplugin/error/configure.zcml
src/zamplugin/error/error.pt
src/zamplugin/error/error_as_text.pt
src/zamplugin/error/errors.pt
src/zamplugin/error/ftesting.zcml
src/zamplugin/error/interfaces.py
src/zamplugin/error/manager.py
src/zamplugin/error/menu.py
src/zamplugin/error/menu.zcml
src/zamplugin/error/plugin.py
src/zamplugin/error/plugin.zcml
src/zamplugin/error/tests.py
src/zamplugin/error/text_lines_input.pt
src/zamplugin/error/widget.py